simplebot_memes_es.py
simplebot_memes_es-1.1.0.dist-info/LICENSE
simplebot_memes_es-1.1.0.dist-info/METADATA
simplebot_memes_es-1.1.0.dist-info/WHEEL
simplebot_memes_es-1.1.0.dist-info/entry_points.txt
simplebot_memes_es-1.1.0.dist-info/top_level.txt
simplebot_memes_es-1.1.0.dist-info/RECORD
